mriqc/__init__.py
mriqc/__main__.py
mriqc/_version.py
mriqc/_warnings.py
mriqc/config.py
mriqc/conftest.py
mriqc/messages.py
mriqc/testing.py
mriqc/bin/__init__.py
mriqc/bin/abide2bids.py
mriqc/bin/dfcheck.py
mriqc/bin/fs2gif.py
mriqc/bin/labeler.py
mriqc/bin/messages.py
mriqc/bin/mriqcwebapi_test.py
mriqc/bin/nib_hash.py
mriqc/bin/subject_wrangler.py
mriqc/cli/__init__.py
mriqc/cli/parser.py
mriqc/cli/run.py
mriqc/cli/version.py
mriqc/cli/workflow.py
mriqc/data/NOTICE
mriqc/data/__init__.py
mriqc/data/bootstrap-anat.yml
mriqc/data/bootstrap-dwi.yml
mriqc/data/bootstrap-func.yml
mriqc/data/config-example.toml
mriqc/data/config.py
mriqc/data/fsexport.tcl
mriqc/data/itk_identity.tfm
mriqc/data/reports/group.html
mriqc/data/reports/embed_resources/boxplots.css
mriqc/data/reports/embed_resources/boxplots.js
mriqc/data/reports/embed_resources/d3.min.js
mriqc/data/reports/resources/DO_NOT_REMOVE_OR_MODIFY
mriqc/data/reports/resources/boxplots.css
mriqc/data/reports/resources/boxplots.js
mriqc/data/reports/resources/d3.min.js
mriqc/data/testdata/group_T1w.tsv
mriqc/data/testdata/group_bold.tsv
mriqc/data/tests/gh1086-ds004134.oracle
mriqc/data/tests/gh921-dmd-20220428-0.oracle
mriqc/data/tests/gh921-dmd-20230319-0.oracle
mriqc/data/tests/ds000005/CHANGES
mriqc/data/tests/ds000005/README
mriqc/data/tests/ds000005/dataset_description.json
mriqc/data/tests/ds000005/participants.tsv
mriqc/data/tests/ds000005/task-mixedgamblestask_bold.json
mriqc/data/tests/ds000005/sub-01/anat/sub-01_T1w.nii.gz
mriqc/data/tests/ds000005/sub-01/anat/sub-01_inplaneT2.nii.gz
mriqc/data/tests/ds000005/sub-01/func/sub-01_task-mixedgamblestask_run-01_bold.json
mriqc/data/tests/ds000005/sub-01/func/sub-01_task-mixedgamblestask_run-01_bold.nii.gz
mriqc/data/tests/ds000005/sub-01/func/sub-01_task-mixedgamblestask_run-01_events.tsv
mriqc/data/tests/ds000005/sub-01/func/sub-01_task-mixedgamblestask_run-02_bold.json
mriqc/data/tests/ds000005/sub-01/func/sub-01_task-mixedgamblestask_run-02_bold.nii.gz
mriqc-24.0.2.dist-info/METADATA
mriqc-24.0.2.dist-info/WHEEL
mriqc-24.0.2.dist-info/entry_points.txt
mriqc-24.0.2.dist-info/licenses/LICENSE
mriqc-24.0.2.dist-info/licenses/NOTICE
mriqc-24.0.2.dist-info/RECORD
