Metadata-Version: 2.3
Name: mriqc
Version: 24.0.2
Summary: Automated Quality Control and visual reports for Quality Assessment of structural (T1w, T2w) and functional MRI of the brain.
Project-URL: Docker Images, https://hub.docker.com/r/nipreps/mriqc/tags/
Project-URL: Documentation, https://mriqc.readthedocs.io/
Project-URL: Homepage, https://github.com/nipreps/mriqc
Project-URL: Manuscript, https://doi.org/10.1371/journal.pone.0184661
Project-URL: NiPreps, https://www.nipreps.org/
Project-URL: Sci Dat Paper, https://doi.org/10.1038/s41597-019-0035-4
Project-URL: Web API, https://mriqc.nimh.nih.gov/
Author-email: The NiPreps Developers <nipreps@gmail.com>
License-Expression: Apache-2.0
License-File: LICENSE
License-File: NOTICE
Classifier: Development Status :: 5 - Production/Stable
Classifier: Intended Audience :: Science/Research
Classifier: License :: OSI Approved :: Apache Software License
Classifier: Programming Language :: Python :: 3.8
Classifier: Programming Language :: Python :: 3.9
Classifier: Programming Language :: Python :: 3.10
Classifier: Programming Language :: Python :: 3.11
Classifier: Programming Language :: Python :: 3.12
Classifier: Topic :: Scientific/Engineering :: Bio-Informatics
Classifier: Topic :: Scientific/Engineering :: Image Recognition
Requires-Python: >=3.8
Requires-Dist: acres
Requires-Dist: dipy
Requires-Dist: importlib-resources; python_version < '3.9'
Requires-Dist: markupsafe~=2.0.1
Requires-Dist: matplotlib
Requires-Dist: migas>=0.4.0
Requires-Dist: mriqc-learn
Requires-Dist: nibabel>=3.0.1
Requires-Dist: nilearn>=0.5.1
Requires-Dist: nipype~=1.4
Requires-Dist: nireports~=24.0.2
Requires-Dist: nitransforms~=24.0
Requires-Dist: niworkflows~=1.10.1
Requires-Dist: numpy~=1.20
Requires-Dist: orjson
Requires-Dist: pandas
Requires-Dist: pybids>=0.15.6
Requires-Dist: pyyaml
Requires-Dist: scikit-learn
Requires-Dist: scipy~=1.8
Requires-Dist: statsmodels
Requires-Dist: templateflow
Requires-Dist: toml
Requires-Dist: tomli>=1.1.0; python_version < '3.11'
Requires-Dist: torch>=1.10.2
Provides-Extra: all
Requires-Dist: coverage; extra == 'all'
Requires-Dist: datalad; extra == 'all'
Requires-Dist: datalad-osf; extra == 'all'
Requires-Dist: ipython; extra == 'all'
Requires-Dist: jupyter; extra == 'all'
Requires-Dist: mock; extra == 'all'
Requires-Dist: nipy; extra == 'all'
Requires-Dist: nipype; extra == 'all'
Requires-Dist: nirodents>=0.2.8; extra == 'all'
Requires-Dist: nitime; extra == 'all'
Requires-Dist: packaging; extra == 'all'
Requires-Dist: pydot>=1.2.3; extra == 'all'
Requires-Dist: pydotplus; extra == 'all'
Requires-Dist: pytest; extra == 'all'
Requires-Dist: pytest-cov; extra == 'all'
Requires-Dist: pytest-env; extra == 'all'
Requires-Dist: pytest-xdist; extra == 'all'
Requires-Dist: scikit-image; extra == 'all'
Requires-Dist: seaborn; extra == 'all'
Requires-Dist: sphinx-argparse; extra == 'all'
Requires-Dist: sphinx-rtd-theme; extra == 'all'
Requires-Dist: sphinx~=5.0; extra == 'all'
Requires-Dist: xvfbwrapper; extra == 'all'
Provides-Extra: container
Requires-Dist: datalad; extra == 'container'
Requires-Dist: datalad-osf; extra == 'container'
Provides-Extra: dev
Requires-Dist: ruff; extra == 'dev'
Provides-Extra: doc
Requires-Dist: nipype; extra == 'doc'
Requires-Dist: packaging; extra == 'doc'
Requires-Dist: pydot>=1.2.3; extra == 'doc'
Requires-Dist: pydotplus; extra == 'doc'
Requires-Dist: sphinx-argparse; extra == 'doc'
Requires-Dist: sphinx-rtd-theme; extra == 'doc'
Requires-Dist: sphinx~=5.0; extra == 'doc'
Provides-Extra: docs
Requires-Dist: nipype; extra == 'docs'
Requires-Dist: packaging; extra == 'docs'
Requires-Dist: pydot>=1.2.3; extra == 'docs'
Requires-Dist: pydotplus; extra == 'docs'
Requires-Dist: sphinx-argparse; extra == 'docs'
Requires-Dist: sphinx-rtd-theme; extra == 'docs'
Requires-Dist: sphinx~=5.0; extra == 'docs'
Provides-Extra: notebook
Requires-Dist: ipython; extra == 'notebook'
Requires-Dist: jupyter; extra == 'notebook'
Requires-Dist: nipy; extra == 'notebook'
Provides-Extra: other
Requires-Dist: nitime; extra == 'other'
Requires-Dist: scikit-image; extra == 'other'
Requires-Dist: seaborn; extra == 'other'
Requires-Dist: xvfbwrapper; extra == 'other'
Provides-Extra: others
Requires-Dist: nitime; extra == 'others'
Requires-Dist: scikit-image; extra == 'others'
Requires-Dist: seaborn; extra == 'others'
Requires-Dist: xvfbwrapper; extra == 'others'
Provides-Extra: rodents
Requires-Dist: nirodents>=0.2.8; extra == 'rodents'
Provides-Extra: test
Requires-Dist: coverage; extra == 'test'
Requires-Dist: mock; extra == 'test'
Requires-Dist: pytest; extra == 'test'
Requires-Dist: pytest-cov; extra == 'test'
Requires-Dist: pytest-env; extra == 'test'
Requires-Dist: pytest-xdist; extra == 'test'
Provides-Extra: tests
Requires-Dist: coverage; extra == 'tests'
Requires-Dist: mock; extra == 'tests'
Requires-Dist: pytest; extra == 'tests'
Requires-Dist: pytest-cov; extra == 'tests'
Requires-Dist: pytest-env; extra == 'tests'
Requires-Dist: pytest-xdist; extra == 'tests'
